import_export_dramatiq/__init__.py
import_export_dramatiq/admin.py
import_export_dramatiq/admin_actions.py
import_export_dramatiq/model_config.py
import_export_dramatiq/tasks.py
import_export_dramatiq/migrations/0001_initial.py
import_export_dramatiq/migrations/__init__.py
import_export_dramatiq/models/__init__.py
import_export_dramatiq/models/exportjob.py
import_export_dramatiq/models/importjob.py
django_import_export_dramatiq-1.0.0.dist-info/LICENSE
django_import_export_dramatiq-1.0.0.dist-info/METADATA
django_import_export_dramatiq-1.0.0.dist-info/WHEEL
django_import_export_dramatiq-1.0.0.dist-info/top_level.txt
django_import_export_dramatiq-1.0.0.dist-info/RECORD
