Metadata-Version: 2.1
Name: django-import-export-dramatiq
Version: 1.0.0
Summary: Process long running django imports and exports in dramatiq
Home-page: https://github.com/q0w/django-import-export-dramatiq
Author: q0w
License: MIT
Platform: UNKNOWN
Classifier: Environment :: Web Environment
Classifier: Framework :: Django
Classifier: License :: OSI Approved :: MIT License
Classifier: Operating System :: OS Independent
Classifier: Programming Language :: Python :: 3
Classifier: Programming Language :: Python :: 3 :: Only
Classifier: Programming Language :: Python :: 3.6
Classifier: Programming Language :: Python :: 3.7
Classifier: Programming Language :: Python :: 3.8
Classifier: Programming Language :: Python :: 3.9
Requires-Python: >=3.6
License-File: LICENSE
Requires-Dist: django
Requires-Dist: django-author
Requires-Dist: django-dramatiq
Requires-Dist: django-import-export
